stlib/__init__.py
stlib/client.py
stlib/community.py
stlib/internals.py
stlib/login.py
stlib/plugins.py
stlib/py.typed
stlib/steam_api64.dll
stlib/steamworks.cp310-win_amd64.pyd
stlib/universe.py
stlib/utils.py
stlib/webapi.py
stlib-2.3.1.dist-info/LICENSE.md
stlib-2.3.1.dist-info/METADATA
stlib-2.3.1.dist-info/WHEEL
stlib-2.3.1.dist-info/top_level.txt
stlib-2.3.1.dist-info/RECORD
