Metadata-Version: 2.1
Name: stlib
Version: 2.3.1
Summary: Async library that provides features related to Steam client and compatible stuffs
Author: Lara Maia
Author-email: dev@lara.monster
License: GPLv3
Project-URL: homepage, https://github.com/calendulish/stlib
Project-URL: documentation, https://lara.monster/stlib
Project-URL: repository, https://github.com
Project-URL: changelog, https://github.com/calendulish/stlib/releases
Keywords: steam,valve
Classifier: Development Status :: 4 - Beta
Classifier: Intended Audience :: Developers
Classifier: Topic :: Games/Entertainment
Classifier: License :: OSI Approved :: GNU General Public License v3 (GPLv3)
Classifier: Operating System :: POSIX :: Linux
Classifier: Operating System :: Microsoft :: Windows
Classifier: Programming Language :: Python :: 3 :: Only
Classifier: Programming Language :: Python :: 3.10
Classifier: Programming Language :: Python :: 3.11
Classifier: Programming Language :: Python :: 3.12
Classifier: Typing :: Typed
Requires-Python: >=3.10
License-File: LICENSE.md
Requires-Dist: aiohttp
Requires-Dist: beautifulsoup4
Requires-Dist: rsa
Provides-Extra: plugins
Requires-Dist: stlib-plugins; extra == "plugins"
